pyIUDX/__init__.py
pyIUDX/auth/__init__.py
pyIUDX/auth/auth.py
pyIUDX/cat/__init__.py
pyIUDX/cat/cat.py
pyIUDX/rs/__init__.py
pyIUDX/rs/item.py
pyIUDX/rs/rs.py
pyIUDX-1.0.1.dist-info/LICENSE.txt
pyIUDX-1.0.1.dist-info/METADATA
pyIUDX-1.0.1.dist-info/WHEEL
pyIUDX-1.0.1.dist-info/top_level.txt
pyIUDX-1.0.1.dist-info/RECORD
