Metadata-Version: 2.1
Name: pyIUDX
Version: 1.0.1
Summary: Python SDK for IUDX.
Home-page: https://github.com/rbccps-iisc/pyIUDX
Author: Mukunth A, Jishnu P, Arun Babu, Rakshit Ramesh
Author-email: mukuntharun@gmail.com, jishnu.jayakumar182@gmail.com, barun@iisc.ac.in, rakshitr@iisc.ac.in
License: GNU General Public License v3.0
Platform: UNKNOWN
Requires-Dist: requests
Requires-Dist: urllib3
